imapy/__init__.py
imapy/connector.py
imapy/email_message.py
imapy/exceptions.py
imapy/imap.py
imapy/mail_folder.py
imapy/packages/__init__.py
imapy/packages/imap_utf7.py
imapy/packages/six.py
imapy/query_builder.py
imapy/structures.py
imapy/utils.py
imapy-1.2.1.dist-info/METADATA
imapy-1.2.1.dist-info/WHEEL
imapy-1.2.1.dist-info/RECORD
